README.rst
setup.py
Thyestes.egg-info/PKG-INFO
Thyestes.egg-info/SOURCES.txt
Thyestes.egg-info/dependency_links.txt
Thyestes.egg-info/entry_points.txt
Thyestes.egg-info/requires.txt
Thyestes.egg-info/top_level.txt
tests_manual/__init__.py
tests_unit/__init__.py
tests_unit/test_restarttimer.py
tests_unit/test_spawntimer.py
tests_unit/test_timer.py
tests_unit/test_timerfactory.py
tests_unit/test_timerservice.py
tests_unit/test_validateconfig.py
thyestes/__init__.py
thyestes/acontroller.py
thyestes/restarttimer.py
thyestes/spawntimer.py
thyestes/timer.py
thyestes/timerfactory.py
thyestes/timerservice.py
thyestes/schema/__init__.py
thyestes/schema/schema.py