Metadata-Version: 1.2
Name: Thyestes
Version: 0.1.2
Summary: Thyestes it a timer microservice. Listens on topics for specific messages, starts a timer when such a messages has been received and publishes a predefined message after the timer expired.
Home-page: https://gitlab.com/pelops/skeiron/
Author: Tobias Gawron-Deutsch
Author-email: tobias@strix.at
License: MIT license
Keywords: mqtt forward echo ping service
Platform: UNKNOWN
Classifier: Development Status :: 4 - Beta
Classifier: Environment :: Console
Classifier: Environment :: No Input/Output (Daemon)
Classifier: Intended Audience :: Developers
Classifier: Programming Language :: Python :: 3
Classifier: Topic :: Utilities
Classifier: Topic :: Home Automation
Classifier: License :: OSI Approved :: MIT License
Requires-Python: >=3.5
